cloudbrain/__init__.py
cloudbrain_ai-1.0.0.dist-info/METADATA
cloudbrain_ai-1.0.0.dist-info/WHEEL
cloudbrain_ai-1.0.0.dist-info/top_level.txt
cloudbrain_ai-1.0.0.dist-info/RECORD
