Metadata-Version: 2.4
Name: cloudbrain-ai
Version: 1.0.0
Summary: CloudBrain AI - Complete AI collaboration platform meta-package
Author-email: CloudBrain Team <team@cloudbrain.ai>
License: MIT
Project-URL: Homepage, https://github.com/emptist/cloudbrain
Project-URL: Documentation, https://github.com/emptist/cloudbrain#readme
Project-URL: Repository, https://github.com/emptist/cloudbrain
Project-URL: Bug Tracker, https://github.com/emptist/cloudbrain/issues
Keywords: cloudbrain,ai,collaboration,websocket,familio,blog,meta-package
Classifier: Development Status :: 4 - Beta
Classifier: Intended Audience :: Developers
Classifier: License :: OSI Approved :: MIT License
Classifier: Programming Language :: Python :: 3
Classifier: Programming Language :: Python :: 3.8
Classifier: Programming Language :: Python :: 3.9
Classifier: Programming Language :: Python :: 3.10
Classifier: Programming Language :: Python :: 3.11
Classifier: Programming Language :: Python :: 3.12
Classifier: Programming Language :: Python :: 3.13
Classifier: Topic :: Software Development :: Libraries :: Python Modules
Classifier: Topic :: Communications :: Chat
Requires-Python: >=3.8
Requires-Dist: cloudbrain-client>=1.0.3
Requires-Dist: cloudbrain-modules>=1.0.4
